{"name":"Meteor-atlassian-crowd","tagline":"A Meteor package for atlassian crowd","body":"# meteor-atlassian-crowd\r\nA Meteor package for the Atlassian Crowd nodejs module.\r\n\r\n## Status\r\n\r\nThis is v0.0.1 of the meteor package. We are just now begining to test.\r\n\r\n## Setup\r\n\r\n* Clone this repo\r\n* <code>cd /path/to/meteor/app<code>\r\n* <code>mkdir packages<code>\r\n* <code>ln -s /path/to/meteor-atlassian-crowd packages/meteor-atlassian-crowd<code>\r\n* <code>meteor add elosoman:meteor-atlassian-crowd<code>\r\n* Create an instance of crowd with your config options.\r\n* <code>\r\nvar atlassianCrowdConfig = { };\r\ncrowd = atlassianCrowd( atlassianCrowdConfg );\r\n<code>\r\n\r\nFuture releases may be published through meteor atmospherejs ... stay tuned.\r\n\r\n## Documentation\r\n\r\nAccess the module in js as <code>AtlassianCrowd</code>.\r\n\r\nYou can create an instance of <code>AtlassianCrowd</code> by passing it an options doc.\r\n\r\n<pre>\r\nvar options = {\r\n  \"crowd\": {\r\n    \"base\": \"http://crowd.yourdomain.com:8059/crowd/\", \r\n  },\r\n  \"application\": {\r\n    \"name\": \"username\",\r\n    \"password\": \"password\"\r\n  }\r\n}\r\n\r\ncrowd = new AtlassianCrowd(options);\r\n</pre>\r\n\r\n## Miscellany\r\n\r\nFurther documenation about Atlassian Crow applications.\r\nhttps://confluence.atlassian.com/display/CROWD/Adding+an+Application#AddinganApplication-add\r\n\r\n## Kudos\r\n\r\nUses the node package to facilitate access and api calls to atlassian-crowd package.\r\nhttps://www.npmjs.com/package/atlassian-crowd\r\n\r\n","google":"","note":"Don't delete this file! It's used internally to help with page regeneration."}